NetEaseMusicApi/RawApi.py
NetEaseMusicApi/SortedApi.py
NetEaseMusicApi/__init__.py
NetEaseMusicApi-1.0.3.dist-info/DESCRIPTION.rst
NetEaseMusicApi-1.0.3.dist-info/METADATA
NetEaseMusicApi-1.0.3.dist-info/RECORD
NetEaseMusicApi-1.0.3.dist-info/WHEEL
NetEaseMusicApi-1.0.3.dist-info/metadata.json
NetEaseMusicApi-1.0.3.dist-info/top_level.txt
