Metadata-Version: 1.1
Name: NetEaseMusicApi
Version: 1.0.3
Summary: A complete NetEase cloud music api
Home-page: https://github.com/littlecodersh/NetEaseMusicApi
Author: LittleCoder
Author-email: i7meavnktqegm1b@qq.com
License: MIT
Keywords: NetEase music api python
Platform: UNKNOWN
Classifier: Development Status :: 3 - Alpha
Classifier: Intended Audience :: Developers
Classifier: Topic :: Software Development :: Libraries :: Python Modules
Classifier: License :: OSI Approved :: MIT License
Classifier: Programming Language :: Python :: 2
Classifier: Programming Language :: Python :: 2.6
Classifier: Programming Language :: Python :: 2.7
Classifier: Programming Language :: Python :: 3
Classifier: Programming Language :: Python :: 3.3
Classifier: Programming Language :: Python :: 3.4
Classifier: Programming Language :: Python :: 3.5
